{
  "_fv": 73,
  "_type": "loottable",
  "definition": {
    "type": "Chest",
    "pools": [
      {
        "minrolls": 1,
        "maxrolls": 2,
        "minbonusrolls": 1,
        "maxbonusrolls": 5,
        "hasbonusrolls": true,
        "entries": [
          {
            "type": "item",
            "item": {
              "value": "CUSTOM:StainlessSteel"
            },
            "weight": 50,
            "minCount": 1,
            "maxCount": 10,
            "minEnchantmentLevel": 0,
            "maxEnchantmentLevel": 0,
            "affectedByFortune": false,
            "explosionDecay": false,
            "silkTouchMode": 0
          },
          {
            "type": "item",
            "item": {
              "value": "CUSTOM:BlockOfStainlessSteel"
            },
            "weight": 10,
            "minCount": 1,
            "maxCount": 5,
            "minEnchantmentLevel": 0,
            "maxEnchantmentLevel": 0,
            "affectedByFortune": false,
            "explosionDecay": false,
            "silkTouchMode": 0
          },
          {
            "type": "item",
            "item": {
              "value": "CUSTOM:BloodBagEmpty"
            },
            "weight": 1,
            "minCount": 1,
            "maxCount": 1,
            "minEnchantmentLevel": 0,
            "maxEnchantmentLevel": 0,
            "affectedByFortune": false,
            "explosionDecay": false,
            "silkTouchMode": 0
          },
          {
            "type": "item",
            "item": {
              "value": "CUSTOM:ComputerChip"
            },
            "weight": 1,
            "minCount": 1,
            "maxCount": 1,
            "minEnchantmentLevel": 0,
            "maxEnchantmentLevel": 0,
            "affectedByFortune": false,
            "explosionDecay": false,
            "silkTouchMode": 0
          }
        ]
      }
    ],
    "name": "chests/village_plains_house",
    "namespace": "minecraft"
  }
}